{"chunk_definitions":[{"row":38,"row_count":1,"visible":true,"expansion_state":0,"options":{"engine":"r","label":"setup","include":false,"dev":"png"},"document_id":"BAF808A9","chunk_id":"csetup_chunk","chunk_label":"setup"},{"row":55,"row_count":1,"visible":true,"expansion_state":0,"options":{"engine":"r","label":"explore-structure","dev":"png"},"document_id":"BAF808A9","chunk_id":"csnd9u53if4m5","chunk_label":"explore-structure"},{"row":81,"row_count":1,"visible":true,"expansion_state":0,"options":{"engine":"r","label":"tibble-vs-dataframe","dev":"png"},"document_id":"BAF808A9","chunk_id":"cen7yvnzamx4p","chunk_label":"tibble-vs-dataframe"},{"row":102,"row_count":1,"visible":true,"expansion_state":0,"options":{"engine":"r","label":"column-selection","dev":"png"},"document_id":"BAF808A9","chunk_id":"c5raimfunf0y6","chunk_label":"column-selection"},{"row":114,"row_count":1,"visible":true,"expansion_state":0,"options":{"engine":"r","label":"rename-columns","dev":"png"},"document_id":"BAF808A9","chunk_id":"cf0mxa0qj3y2u","chunk_label":"rename-columns"},{"row":133,"row_count":1,"visible":true,"expansion_state":0,"options":{"engine":"r","label":"calculate-age","dev":"png"},"document_id":"BAF808A9","chunk_id":"ck7iyqc57j13z","chunk_label":"calculate-age"},{"row":148,"row_count":1,"visible":true,"expansion_state":0,"options":{"engine":"r","label":"categorize-cars","dev":"png"},"document_id":"BAF808A9","chunk_id":"c4155o2zvnl2q","chunk_label":"categorize-cars"},{"row":163,"row_count":1,"visible":true,"expansion_state":0,"options":{"engine":"r","label":"basic-filtering","dev":"png"},"document_id":"BAF808A9","chunk_id":"cr2szh4rt0p8l","chunk_label":"basic-filtering"},{"row":178,"row_count":1,"visible":true,"expansion_state":0,"options":{"engine":"r","label":"multiple-conditions","dev":"png"},"document_id":"BAF808A9","chunk_id":"c6os2u3a3r7az","chunk_label":"multiple-conditions"},{"row":218,"row_count":1,"visible":true,"expansion_state":0,"options":{"engine":"r","label":"categorical-summaries","dev":"png"},"document_id":"BAF808A9","chunk_id":"cj5y5zcn0n5gu","chunk_label":"categorical-summaries"}],"doc_write_time":1757951324}